{
  "id": "471839",
  "production": "Puppy Dog Pals (18/19)",
  "type": "Television",
  "local": "Los Angeles",
  "startEndDates": "09/17/2018 - TBD",
  "signatoryName": "Mako Entertainment, Inc",
  "contractTitleName": "Basic Cable Agreement for Animated Motion Pictures",
  "businessRepresentative": "Art Duarte",
  "claimsRepresentative": "Deborah Wonder",
  "prodSubType": "TV - Animated Series",
  "madeFor": "Basic Cable",
  "market": "The Disney Channel",
  "contributionPlan": "SAG",
  "shootingLocations": [
    "Burbank, CA United States",
    "Atlanta, GA"
  ]
}