{
  "id": "485798",
  "production": "We Were Samurai (19/20)",
  "type": "New Media",
  "local": "Los Angeles",
  "startEndDates": "08/15/2019 - TBD",
  "signatoryName": "Aeaea LLC",
  "contractTitleName": "New Media Agreement",
  "businessRepresentative": "Erin Cardillo",
  "claimsRepresentative": "Connie Best",
  "prodSubType": "Original Podcast",
  "madeFor": "New Media - Deferrable",
  "market": "Other New Media",
  "contributionPlan": "SAG",
  "shootingLocations": [
    "New York, NY United States"
  ]
}