{
  "id": "491547",
  "production": "Limited Edition (19/20)",
  "type": "New Media",
  "local": "Los Angeles",
  "startEndDates": "08/31/2020 - 09/04/2020",
  "signatoryName": "James Mueller",
  "contractTitleName": "New Media Agreement",
  "businessRepresentative": "Joyce Grant",
  "claimsRepresentative": "Silvia Gerber",
  "prodSubType": "Original Series",
  "madeFor": "New Media - Deferrable",
  "market": "Other New Media",
  "contributionPlan": "SAG",
  "shootingLocations": [
    "Los Angeles, CA United States"
  ]
}