{
  "id": "500051",
  "production": "Servant (20/21)",
  "type": "New Media",
  "local": "New York",
  "startEndDates": "01/09/2020 - TBD",
  "signatoryName": "Uncle George Productions, LLC",
  "contractTitleName": "New Media Independent HBSVOD Agreement",
  "businessRepresentative": "Rose Magcalas",
  "claimsRepresentative": "Ramon Jackson",
  "prodSubType": "Original Series",
  "madeFor": "New Media - High-Budget SVOD/Tier 2",
  "market": "Other New Media",
  "contributionPlan": "SAG",
  "shootingLocations": [
    "Newton Square, PA United States"
  ]
}