{
  "id": "471177",
  "production": "Ledge, The",
  "type": "New Media",
  "local": "Los Angeles",
  "startEndDates": "08/04/2018 - TBD",
  "signatoryName": "Brothers Four Productions, Inc.",
  "contractTitleName": "New Media Agreement",
  "businessRepresentative": "Kamau Talbott",
  "bgClaimsRepresentative": "Toloria Milner",
  "claimsRepresentative": "Deborah Wonder",
  "prodSubType": "Original Other",
  "madeFor": "New Media - Deferrable",
  "market": "YouTube",
  "contributionPlan": "SAG",
  "shootingLocations": [
    "los angeles, CA United States"
  ]
}