{
  "id": "506878",
  "production": "Usagi Yojimbo (20/21)",
  "type": "New Media",
  "local": "New York",
  "startEndDates": "08/04/2020 - TBD",
  "signatoryName": "Usagi Productions LLC",
  "contractTitleName": "High Budget New Media Animation Agreement",
  "businessRepresentative": "Anny Edinchikyan",
  "claimsRepresentative": "Emmy Ferguson",
  "prodSubType": "Original Series",
  "madeFor": "New Media - High-Budget SVOD/Tier 2",
  "market": "Netflix",
  "contributionPlan": "SAG",
  "shootingLocations": [
    "Los Angeles, CA United States",
    "Paris, FR France"
  ]
}