{
  "id": "508242",
  "production": "Outer Banks (20/21)",
  "type": "New Media",
  "local": "Atlanta",
  "startEndDates": "08/30/2020 - 02/19/2021",
  "signatoryName": "Narrow Isle Productions, LLC",
  "contractTitleName": "New Media Netflix Agreement",
  "businessRepresentative": "Sara Lissner",
  "claimsRepresentative": "Melissa Goodman",
  "prodSubType": "Original Series",
  "madeFor": "New Media - High-Budget SVOD/Tier 1",
  "market": "Netflix",
  "contributionPlan": "SAG",
  "shootingLocations": [
    "unspecified, SC United States"
  ]
}